LICENSE
MANIFEST.in
README.md
setup.cfg
setup.py
honcho_export_systemd/__init__.py
honcho_export_systemd/export_systemd.py
honcho_export_systemd.egg-info/PKG-INFO
honcho_export_systemd.egg-info/SOURCES.txt
honcho_export_systemd.egg-info/dependency_links.txt
honcho_export_systemd.egg-info/entry_points.txt
honcho_export_systemd.egg-info/requires.txt
honcho_export_systemd.egg-info/top_level.txt
honcho_export_systemd/templates/systemd/master.target
honcho_export_systemd/templates/systemd/process.service
honcho_export_systemd/templates/systemd/process_master.target