Metadata-Version: 1.1
Name: honcho-export-systemd
Version: 1.0.0
Summary: systemd exporter for Honcho.
Home-page: https://github.com/benwilber/honcho-export-systemd
Author: Ben Wilber
Author-email: benwilber@gmail.com
License: APACHE
Keywords: sysadmin process procfile honcho systemd
Platform: UNKNOWN
Classifier: Environment :: Console
Classifier: Intended Audience :: Developers
Classifier: Intended Audience :: System Administrators
Classifier: License :: OSI Approved :: MIT License
Classifier: Operating System :: OS Independent
Classifier: Programming Language :: Python
Classifier: Programming Language :: Python :: 2
Classifier: Programming Language :: Python :: 2.6
Classifier: Programming Language :: Python :: 2.7
Classifier: Programming Language :: Python :: 3
Classifier: Programming Language :: Python :: 3.0
Classifier: Programming Language :: Python :: 3.1
Classifier: Programming Language :: Python :: 3.2
Classifier: Programming Language :: Python :: 3.3
Classifier: Programming Language :: Python :: 3.4
